scludam/__init__.py
scludam/cli.py
scludam/cli_analysis.py
scludam/cli_input.py
scludam/cli_utils.py
scludam/detection.py
scludam/fetcher.py
scludam/hkde.py
scludam/masker.py
scludam/membership.py
scludam/pipeline.py
scludam/plots.py
scludam/rutils.py
scludam/shdbscan.py
scludam/stat_tests.py
scludam/synthetic.py
scludam/type_utils.py
scludam/utils.py
scludam-1.0.10.dist-info/licenses/LICENSE
tests/test_detection.py
tests/test_fetcher.py
tests/test_hkde.py
tests/test_membership.py
tests/test_pipeline.py
tests/test_shdbscan.py
tests/test_stat_tests.py
tests/test_synthetic.py
tests/test_utils.py
tests/utils.py
scludam-1.0.10.dist-info/METADATA
scludam-1.0.10.dist-info/WHEEL
scludam-1.0.10.dist-info/top_level.txt
scludam-1.0.10.dist-info/RECORD
