Metadata-Version: 2.4
Name: scludam
Version: 1.0.10
Summary: Star cluster detection and membership estimation based on GAIA data.
Home-page: http://packages.python.org/scludam
Author: Simón Pedro González
Author-email: simon.pedro.g@gmail.com
License: GPL-3
Keywords: star cluster detection membership probabilities
Classifier: Development Status :: 2 - Pre-Alpha
Classifier: Topic :: Scientific/Engineering :: Astronomy
Classifier: License :: OSI Approved :: GNU General Public License v3 (GPLv3)
License-File: LICENSE
Requires-Dist: numpy<2.0,>=1.26.4
Requires-Dist: matplotlib<4.0,>=3.9.4
Requires-Dist: scipy<2.0,>=1.13.1
Requires-Dist: astropy<7.0,>=6.0.1
Requires-Dist: astroquery==0.4.6
Requires-Dist: pandas<3.0,>=2.3.1
Requires-Dist: hdbscan>=0.8.40
Requires-Dist: joblib>=1.1.0
Requires-Dist: scikit-learn>=1.1.3
Requires-Dist: scikit-image>=0.24.0
Requires-Dist: seaborn<0.14,>=0.13.2
Requires-Dist: attrs<26.0,>=25.3.0
Requires-Dist: beartype<0.22,>=0.21.0
Requires-Dist: ordered_set<5.0,>=4.1.0
Requires-Dist: statsmodels>=0.12.2
Requires-Dist: diptest<0.11.0,>=0.10.0
Requires-Dist: typing_extensions<5.0,>=4.14.1
Requires-Dist: tqdm>=4.67.1
Provides-Extra: dev
Requires-Dist: pytest; extra == "dev"
Requires-Dist: pytest-pep8; extra == "dev"
Requires-Dist: pytest-cov; extra == "dev"
Requires-Dist: pytest-mock; extra == "dev"
Requires-Dist: pytest-mpl; extra == "dev"
Requires-Dist: flake8; extra == "dev"
Requires-Dist: black>=22.3.0; extra == "dev"
Requires-Dist: isort; extra == "dev"
Requires-Dist: flake8-black; extra == "dev"
Requires-Dist: flake8-import-order; extra == "dev"
Dynamic: author
Dynamic: author-email
Dynamic: classifier
Dynamic: description
Dynamic: description-content-type
Dynamic: home-page
Dynamic: keywords
Dynamic: license
Dynamic: license-file
Dynamic: provides-extra
Dynamic: requires-dist
Dynamic: summary
